8bit_Alu/rtl/alu_8bit.v
module alu_8bit (
    input  [7:0] A,
    input  [7:0] B,
    input  [2:0] ALU_Sel,
    input        Cin,

    output reg [7:0] Result,
    output reg       Cout,
    output reg       Zero,
    output reg       Negative,
    output reg       Overflow
);

    // Internal signals
    reg [8:0] sum;
    reg [8:0] diff;

    always @(*) begin
        // Defaults (important to avoid latches)
        Result   = 8'b0;
        Cout     = 1'b0;
        Overflow = 1'b0;

        case (ALU_Sel)

            // ADD
            3'b000: begin
                sum     = {1'b0, A} + {1'b0, B} + Cin;
                Result  = sum[7:0];
                Cout    = sum[8];
                Overflow = (~(A[7] ^ B[7])) & (Result[7] ^ A[7]);
            end

            // SUB : A - B
            3'b001: begin
                diff    = {1'b0, A} - {1'b0, B};
                Result  = diff[7:0];
                Cout    = diff[8];
                Overflow = (A[7] ^ B[7]) & (Result[7] ^ A[7]);
            end

            // AND
            3'b010: begin
                Result = A & B;
            end

            // OR
            3'b011: begin
                Result = A | B;
            end

            // XOR
            3'b100: begin
                Result = A ^ B;
            end

            // NOT
            3'b101: begin
                Result = ~A;
            end

            // Shift Left
            3'b110: begin
                Result = A << 1;
                Cout   = A[7];
            end

            // Shift Right
            3'b111: begin
                Result = A >> 1;
                Cout   = A[0];
            end

            default: begin
                Result = 8'b0;
            end
        endcase

        // Flags
        Zero     = (Result == 8'b0);
        Negative = Result[7];

    end

endmodule

8bit_Alu/rtl/alu_8bit_top.v
module alu_8bit_top (
    input        clk,
    input        rst,
    input  [7:0] A,
    input  [7:0] B,
    input  [2:0] ALU_Sel,
    input        Cin,
    output [7:0] Result
);

    reg [7:0] A_r, B_r;
    reg [2:0] Sel_r;
    reg       Cin_r;
    wire [7:0] Result_w;

    always @(posedge clk or posedge rst) begin
        if (rst) begin
            A_r   <= 8'b0;
            B_r   <= 8'b0;
            Sel_r <= 3'b0;
            Cin_r <= 1'b0;
        end else begin
            A_r   <= A;
            B_r   <= B;
            Sel_r <= ALU_Sel;
            Cin_r <= Cin;
        end
    end

    alu_8bit u_alu (
        .A(A_r),
        .B(B_r),
        .ALU_Sel(Sel_r),
        .Cin(Cin_r),
        .Result(Result_w),
        .Cout(),
        .Zero(),
        .Negative(),
        .Overflow()
    );

    assign Result = Result_w;

endmodule

8bit_Alu/rtl/tb_alu_8bit.v
`timescale 1ns/1ps

module tb_alu_8bit;

    reg         clk;
    reg         rst;
    reg  [7:0]  A;
    reg  [7:0]  B;
    reg  [2:0]  ALU_Sel;
    reg         Cin;

    wire [7:0]  Result;

    // Instantiate DUT (TOP MODULE)
    alu_8bit_top dut (
        .clk(clk),
        .rst(rst),
        .A(A),
        .B(B),
        .ALU_Sel(ALU_Sel),
        .Cin(Cin),
        .Result(Result)
    );

    // Clock generation: 100 MHz (10 ns period)
    always #5 clk = ~clk;

    initial begin
        // Dump waves
        $dumpfile("alu_8bit.vcd");
        $dumpvars(0, tb_alu_8bit);

        // Initialize
        clk     = 0;
        rst     = 1;
        A       = 0;
        B       = 0;
        ALU_Sel = 0;
        Cin     = 0;

        #20;
        rst = 0;

        // ---------------------------
        // ADD
        // ---------------------------
        ALU_Sel = 3'b000;
        A = 8'd10; B = 8'd5; Cin = 0;
        #10;

        A = 8'd200; B = 8'd100; Cin = 0;
        #10;

        // ---------------------------
        // SUB
        // ---------------------------
        ALU_Sel = 3'b001;
        A = 8'd50; B = 8'd20;
        #10;

        A = 8'd20; B = 8'd50;
        #10;

        // ---------------------------
        // AND
        // ---------------------------
        ALU_Sel = 3'b010;
        A = 8'hAA; B = 8'h0F;
        #10;

        // ---------------------------
        // OR
        // ---------------------------
        ALU_Sel = 3'b011;
        A = 8'h55; B = 8'h0F;
        #10;

        // ---------------------------
        // XOR
        // ---------------------------
        ALU_Sel = 3'b100;
        A = 8'hFF; B = 8'h0F;
        #10;

        // ---------------------------
        // NOT
        // ---------------------------
        ALU_Sel = 3'b101;
        A = 8'h0F;
        #10;

        // ---------------------------
        // SHIFT LEFT
        // ---------------------------
        ALU_Sel = 3'b110;
        A = 8'b1001_0001;
        #10;

        // ---------------------------
        // SHIFT RIGHT
        // ---------------------------
        ALU_Sel = 3'b111;
        A = 8'b1001_0001;
        #10;

        #20;
        $finish;
    end

endmodule

8bit_Alu/rtl/alu_8bit.vcd
$date
	Mon Jan 12 22:29:42 2026
$end
$version
	Icarus Verilog
$end
$timescale
	1ps
$end
$scope module tb_alu_8bit $end
$var wire 8 ! Result [7:0] $end
$var reg 8 " A [7:0] $end
$var reg 3 # ALU_Sel [2:0] $end
$var reg 8 $ B [7:0] $end
$var reg 1 % Cin $end
$var reg 1 & clk $end
$var reg 1 ' rst $end
$scope module dut $end
$var wire 8 ( A [7:0] $end
$var wire 3 ) ALU_Sel [2:0] $end
$var wire 8 * B [7:0] $end
$var wire 1 % Cin $end
$var wire 8 + Result [7:0] $end
$var wire 1 & clk $end
$var wire 1 ' rst $end
$var wire 8 , Result_w [7:0] $end
$var reg 8 - A_r [7:0] $end
$var reg 8 . B_r [7:0] $end
$var reg 1 / Cin_r $end
$var reg 3 0 Sel_r [2:0] $end
$scope module u_alu $end
$var wire 8 1 A [7:0] $end
$var wire 3 2 ALU_Sel [2:0] $end
$var wire 8 3 B [7:0] $end
$var wire 1 / Cin $end
$var reg 1 4 Cout $end
$var reg 1 5 Negative $end
$var reg 1 6 Overflow $end
$var reg 8 7 Result [7:0] $end
$var reg 1 8 Zero $end
$var reg 9 9 diff [8:0] $end
$var reg 9 : sum [8:0] $end
$upscope $end
$upscope $end
$upscope $end
$enddefinitions $end
#0
$dumpvars
b0 :
bx 9
18
b0 7
06
05
04
b0 3
b0 2
b0 1
b0 0
0/
b0 .
b0 -
b0 ,
b0 +
b0 *
b0 )
b0 (
1'
0&
0%
b0 $
b0 #
b0 "
b0 !
$end
#5000
1&
#10000
0&
#15000
1&
#20000
0&
b101 $
b101 *
b1010 "
b1010 (
0'
#25000
08
b1111 !
b1111 +
b1111 ,
b1111 7
b1111 :
b101 .
b101 3
b1010 -
b1010 1
1&
#30000
0&
b1100100 $
b1100100 *
b11001000 "
b11001000 (
#35000
14
b100101100 :
b101100 !
b101100 +
b101100 ,
b101100 7
b1100100 .
b1100100 3
b11001000 -
b11001000 1
1&
#40000
0&
b10100 $
b10100 *
b110010 "
b110010 (
b1 #
b1 )
#45000
b11110 9
04
b11110 !
b11110 +
b11110 ,
b11110 7
b1 0
b1 2
b10100 .
b10100 3
b110010 -
b110010 1
1&
#50000
0&
b110010 $
b110010 *
b10100 "
b10100 (
#55000
15
14
b111100010 9
b11100010 !
b11100010 +
b11100010 ,
b11100010 7
b110010 .
b110010 3
b10100 -
b10100 1
1&
#60000
0&
b1111 $
b1111 *
b10101010 "
b10101010 (
b10 #
b10 )
#65000
05
04
b1010 !
b1010 +
b1010 ,
b1010 7
b10 0
b10 2
b1111 .
b1111 3
b10101010 -
b10101010 1
1&
#70000
0&
b1010101 "
b1010101 (
b11 #
b11 )
#75000
b1011111 !
b1011111 +
b1011111 ,
b1011111 7
b11 0
b11 2
b1010101 -
b1010101 1
1&
#80000
0&
b11111111 "
b11111111 (
b100 #
b100 )
#85000
15
b11110000 !
b11110000 +
b11110000 ,
b11110000 7
b100 0
b100 2
b11111111 -
b11111111 1
1&
#90000
0&
b1111 "
b1111 (
b101 #
b101 )
#95000
b11110000 !
b11110000 +
b11110000 ,
b11110000 7
b101 0
b101 2
b1111 -
b1111 1
1&
#100000
0&
b10010001 "
b10010001 (
b110 #
b110 )
#105000
05
14
b100010 !
b100010 +
b100010 ,
b100010 7
b110 0
b110 2
b10010001 -
b10010001 1
1&
#110000
0&
b111 #
b111 )
#115000
14
b1001000 !
b1001000 +
b1001000 ,
b1001000 7
b111 0
b111 2
1&
